[{"first_name":"Eve","last_name":"Ghioni","email":"eghioni0@printfriendly.com","gender":"Female","age":43,"car":"Opel","job":"Accounting Assistant IV","favourite_film":"Thriller"},
{"first_name":"Eloisa","last_name":"Faltskog","email":"efaltskog1@shutterfly.com","gender":"Female","age":77,"car":"Renault","job":"Recruiter","favourite_film":"Thriller"},
{"first_name":"Laurene","last_name":"Wickey","email":"lwickey2@guardian.co.uk","gender":"Female","age":26,"car":"Opel","job":"Director of Sales","favourite_film":"Thriller"},
{"first_name":"Orlan","last_name":"Scutching","email":"oscutching3@unc.edu","gender":"Male","age":36,"car":"Opel","job":"Senior Developer","favourite_film":"Thriller"},
{"first_name":"Darrin","last_name":"Genever","email":"dgenever4@taobao.com","gender":"Male","age":38,"car":"Renault","job":"Social Worker","favourite_film":"Comedy"},
{"first_name":"Far","last_name":"Petroulis","email":"fpetroulis5@google.co.uk","gender":"Male","age":23,"car":"Ford","job":"Media Manager I","favourite_film":"Drama"},
{"first_name":"Wiley","last_name":"Grishmanov","email":"wgrishmanov6@t-online.de","gender":"Male","age":50,"car":"Renault","job":"Registered Nurse","favourite_film":"Thriller"},
{"first_name":"Lock","last_name":"Ley","email":"lley7@jimdo.com","gender":"Male","age":37,"car":"Mazda","job":"Sales Associate","favourite_film":"Thriller"},
{"first_name":"Charissa","last_name":"Kildale","email":"ckildale8@addthis.com","gender":"Female","age":78,"car":"Opel","job":"Desktop Support Technician","favourite_film":"Drama"},
{"first_name":"Gerik","last_name":"Dainton","email":"gdainton9@ocn.ne.jp","gender":"Male","age":66,"car":"Renault","job":"Nurse Practicioner","favourite_film":"Thriller"},
{"first_name":"Ario","last_name":"MacNeachtain","email":"amacneachtaina@yandex.ru","gender":"Male","age":48,"car":"Renault","job":"Information Systems Manager","favourite_film":"Thriller"},
{"first_name":"Nesta","last_name":"Marc","email":"nmarcb@uiuc.edu","gender":"Female","age":27,"car":"Renault","job":"Quality Engineer","favourite_film":"Thriller"},
{"first_name":"Tybalt","last_name":"Wraggs","email":"twraggsc@apple.com","gender":"Male","age":31,"car":"Mazda","job":"Help Desk Technician","favourite_film":"Thriller"},
{"first_name":"Maddalena","last_name":"Robak","email":"mrobakd@cdbaby.com","gender":"Female","age":27,"car":"Renault","job":"Administrative Assistant III","favourite_film":"Thriller"},
{"first_name":"Oliviero","last_name":"Peaseman","email":"opeasemane@apple.com","gender":"Male","age":68,"car":"Renault","job":"Quality Control Specialist","favourite_film":"Action"},
{"first_name":"Vanya","last_name":"Chiles","email":"vchilesf@ehow.com","gender":"Male","age":21,"car":"Renault","job":"Human Resources Manager","favourite_film":"Thriller"},
{"first_name":"Ines","last_name":"Dmiterko","email":"idmiterkog@ucsd.edu","gender":"Female","age":44,"car":"Renault","job":"Developer I","favourite_film":"Thriller"},
{"first_name":"Fidel","last_name":"Woolnough","email":"fwoolnoughh@scribd.com","gender":"Male","age":64,"car":"Ford","job":"Environmental Specialist","favourite_film":"Thriller"},
{"first_name":"Allistir","last_name":"Holliar","email":"aholliari@nsw.gov.au","gender":"Male","age":24,"car":"Opel","job":"GIS Technical Architect","favourite_film":"Comedy"},
{"first_name":"Melessa","last_name":"Skittrall","email":"mskittrallj@webeden.co.uk","gender":"Female","age":73,"car":"Renault","job":"Financial Advisor","favourite_film":"Thriller"}]